fowl/#messages.py#
fowl/README.rst
fowl/__init__.py
fowl/__main__.py
fowl/_proto.py
fowl/_tui.py
fowl/api.py
fowl/chicken.py
fowl/cli.py
fowl/messages.py
fowl/observer.py
fowl/status.py
fowl/tcp.py
fowl/visual.py
fowl/test/__init__.py
fowl/test/conftest.py
fowl/test/test_cli.py
fowl/test/test_commands.py
fowl/test/test_forward.py
fowl/test/test_observer.py
fowl/test/test_tcp.py
fowl/test/util.py
fowl-25.9.0.dist-info/METADATA
fowl-25.9.0.dist-info/WHEEL
fowl-25.9.0.dist-info/entry_points.txt
fowl-25.9.0.dist-info/licenses/LICENSE
fowl-25.9.0.dist-info/RECORD
