Metadata-Version: 2.4
Name: fowl
Version: 25.9.0
Summary: Forward Over Wormhole Locally provides bi-directional streaming data over secure and durable Dilated magic-wormhole connections. Secure communication with easy setup.
Author-email: meejah <meejah@meejah.ca>
License: The MIT License (MIT)
License-File: LICENSE
Keywords: cryptography,forwarding,magic-wormhole,private
Classifier: Framework :: Twisted
Classifier: License :: OSI Approved :: MIT License
Classifier: Programming Language :: Python :: 3
Requires-Python: >=3.9
Requires-Dist: attrs
Requires-Dist: click
Requires-Dist: humanize
Requires-Dist: ipaddress
Requires-Dist: magic-wormhole[dilate]>=0.20.0
Requires-Dist: msgpack
Requires-Dist: rich
Requires-Dist: setuptools
Requires-Dist: six
Requires-Dist: twisted
Provides-Extra: dev
Requires-Dist: cuvner; extra == 'dev'
Requires-Dist: dulwich; extra == 'dev'
Requires-Dist: hatch; extra == 'dev'
Requires-Dist: pip-tools; extra == 'dev'
Requires-Dist: readme-renderer; extra == 'dev'
Requires-Dist: sphinx; extra == 'dev'
Requires-Dist: twine; extra == 'dev'
Provides-Extra: test
Requires-Dist: cuvner; extra == 'test'
Requires-Dist: hypothesis; extra == 'test'
Requires-Dist: magic-wormhole-mailbox-server; extra == 'test'
Requires-Dist: pytest; extra == 'test'
Requires-Dist: pytest-cov; extra == 'test'
Requires-Dist: pytest-twisted; extra == 'test'
Requires-Dist: ruff; extra == 'test'
